schism/__init__.py
schism/bridges.py
schism/cli_script.py
schism/configs.py
schism/controllers.py
schism/ext/__init__.py
schism/ext/bridges/__init__.py
schism/ext/bridges/simple_tcp.py
schism/middleware.py
schism/run.py
schism/services.py
schism-0.1.3.dist-info/METADATA
schism-0.1.3.dist-info/WHEEL
schism-0.1.3.dist-info/entry_points.txt
schism-0.1.3.dist-info/RECORD
