Metadata-Version: 2.1
Name: schism
Version: 0.1.3
Summary: Schism is an autowiring library that makes modularity simple in monolithes and simplifies code sharing in microservices.
Home-page: https://github.com/ZechCodes/Schism
License: MIT
Author: ZechCodes
Author-email: hi@zech.codes
Requires-Python: >=3.12,<4.0
Classifier: License :: OSI Approved :: MIT License
Classifier: Programming Language :: Python :: 3
Classifier: Programming Language :: Python :: 3.12
Classifier: Programming Language :: Python :: 3.13
Requires-Dist: bevy (>=2.0.2,<3.0.0)
Requires-Dist: nubby[yaml] (>=0.0.2,<0.0.3)
Requires-Dist: pydantic (>=2.9.2,<3.0.0)
Requires-Dist: pytest-asyncio (>=0.24.0,<0.25.0)
Requires-Dist: tramp (>=0.1.11,<0.2.0)
Project-URL: Repository, https://github.com/ZechCodes/Schism
